huqt_oracle_pysdk/__init__.py
huqt_oracle_pysdk/enums.py
huqt_oracle_pysdk/oracle.py
huqt_oracle_pysdk/request.py
huqt_oracle_pysdk/subscribe.py
huqt_oracle_pysdk/websocket.py
huqt_oracle_pysdk/fbs_gen/client/AddOrderRequest.py
huqt_oracle_pysdk/fbs_gen/client/CancelOrderRequest.py
huqt_oracle_pysdk/fbs_gen/client/ClientRequest.py
huqt_oracle_pysdk/fbs_gen/client/ClientRequestUnion.py
huqt_oracle_pysdk/fbs_gen/client/ConversionRequest.py
huqt_oracle_pysdk/fbs_gen/client/DepositRequest.py
huqt_oracle_pysdk/fbs_gen/client/ExerciseOptionRequest.py
huqt_oracle_pysdk/fbs_gen/client/IssueOptionRequest.py
huqt_oracle_pysdk/fbs_gen/client/OrderType.py
huqt_oracle_pysdk/fbs_gen/client/RevokeSessionRequest.py
huqt_oracle_pysdk/fbs_gen/client/SetSessionRequest.py
huqt_oracle_pysdk/fbs_gen/client/SubscriptionRequest.py
huqt_oracle_pysdk/fbs_gen/client/Tif.py
huqt_oracle_pysdk/fbs_gen/client/UnaryRequest.py
huqt_oracle_pysdk/fbs_gen/client/UnaryRequestUnion.py
huqt_oracle_pysdk/fbs_gen/client/WithdrawRequest.py
huqt_oracle_pysdk/fbs_gen/client/__init__.py
huqt_oracle_pysdk/fbs_gen/gateway/AccountIssuedOption.py
huqt_oracle_pysdk/fbs_gen/gateway/AccountPnl.py
huqt_oracle_pysdk/fbs_gen/gateway/AccountPosition.py
huqt_oracle_pysdk/fbs_gen/gateway/AccountType.py
huqt_oracle_pysdk/fbs_gen/gateway/AddOrderResponse.py
huqt_oracle_pysdk/fbs_gen/gateway/AuctionMeta.py
huqt_oracle_pysdk/fbs_gen/gateway/AuctionMetaUnion.py
huqt_oracle_pysdk/fbs_gen/gateway/ConversionElement.py
huqt_oracle_pysdk/fbs_gen/gateway/ConversionMeta.py
huqt_oracle_pysdk/fbs_gen/gateway/DomainMarketDataStream.py
huqt_oracle_pysdk/fbs_gen/gateway/DomainMarketDataSubscription.py
huqt_oracle_pysdk/fbs_gen/gateway/DomainMetaStream.py
huqt_oracle_pysdk/fbs_gen/gateway/DomainMetaSubscription.py
huqt_oracle_pysdk/fbs_gen/gateway/DomainsStream.py
huqt_oracle_pysdk/fbs_gen/gateway/DomainsSubscription.py
huqt_oracle_pysdk/fbs_gen/gateway/ErrorMessage.py
huqt_oracle_pysdk/fbs_gen/gateway/Fill.py
huqt_oracle_pysdk-0.1.7.dist-info/METADATA
huqt_oracle_pysdk-0.1.7.dist-info/WHEEL
huqt_oracle_pysdk-0.1.7.dist-info/top_level.txt
huqt_oracle_pysdk-0.1.7.dist-info/RECORD
