Metadata-Version: 2.4
Name: huqt_oracle_pysdk
Version: 0.1.7
Summary: HUQT Oracle Python SDK for bot building
Author-email: Haozhe Yang <haozheyang@gmail.com>
License: MIT
Project-URL: Homepage, https://github.com/harvarduqt/python-sdk
Project-URL: Repository, https://github.com/harvarduqt/python-sdk
Requires-Python: >=3.10
Requires-Dist: flatbuffers==25.2.10
Requires-Dist: websockets==11.0.3
Requires-Dist: python-dotenv==1.1.1
